{
  "/_app": "pages/_app.js",
  "/_error": "pages/_error.js",
  "/_document": "pages/_document.js",
  "/404": "pages/404.html",
  "/add-report": "pages/add-report.html",
  "/api/hello": "pages/api/hello.js",
  "/add-resource": "pages/add-resource.html",
  "/api/route": "pages/api/route.js",
  "/addUser": "pages/addUser.html",
  "/components/ConfirmationModal": "pages/components/ConfirmationModal.html",
  "/components/AdminDasbboard": "pages/components/AdminDasbboard.html",
  "/components/MobileSideBar": "pages/components/MobileSideBar.html",
  "/components/AdminDash": "pages/components/AdminDash.html",
  "/components/ProfileContent": "pages/components/ProfileContent.html",
  "/components/SideBar": "pages/components/SideBar.html",
  "/components/ShowProfile": "pages/components/ShowProfile.html",
  "/components/TopHeade": "pages/components/TopHeade.html",
  "/components/UserDashboard": "pages/components/UserDashboard.html",
  "/components/NewsLetter": "pages/components/NewsLetter.html",
  "/dashboard": "pages/dashboard.html",
  "/": "pages/index.html",
  "/learning-resources": "pages/learning-resources.html",
  "/login": "pages/login.html",
  "/newsletter": "pages/newsletter.html",
  "/project-edit-detail": "pages/project-edit-detail.html",
  "/reseller-benefits": "pages/reseller-benefits.html",
  "/profile": "pages/profile.html",
  "/projectList": "pages/projectList.html",
  "/resource-detail": "pages/resource-detail.html",
  "/users": "pages/users.html",
  "/resource-edit-detail": "pages/resource-edit-detail.html",
  "/user-edit": "pages/user-edit.html",
  "/update-profile": "pages/update-profile.html",
  "/users/[edituser]": "pages/users/[edituser].js"
}